itp17210.v
module parkingManager(input IN,input OUT0,input OUT1,output [31:0] CARS,output [31:0] AVAILABLE,output FULL,output FLOOR0,output FLOOR1);
    wire IN,OUT0,OUT1;
    reg [31:0] CARS;
    reg [31:0] AVAILABLE;
    reg [31:0] zeroFloor;
    reg [31:0] firstFloor;
    reg FULL, FLOOR0, FLOOR1;

    initial begin
        CARS = 2'd00;
        AVAILABLE = 1000;
        zeroFloor = 0;
        firstFloor = 0;
        FULL = 1'b0;
        FLOOR0 = 1'b1;
        FLOOR1 = 1'b1;
    end
    always@(IN or OUT0 or OUT1) begin
        if (IN == 1) begin
            if(AVAILABLE > 0) begin
                CARS  = CARS +1;
                AVAILABLE = AVAILABLE -1;
                if(CARS > 500) begin
                    FLOOR0 = 1'b0;
                    firstFloor = firstFloor +1;
                end else begin
                    zeroFloor = zeroFloor +1;
                end
                if(CARS == 1000) begin
                    FLOOR1 = 1'b0;
                    FULL = 1'b1;
                end
            end
        end
        if ((OUT0 == 1) && (zeroFloor >0) && (zeroFloor <= 500)) begin
            CARS  = CARS -1;
            AVAILABLE = AVAILABLE +1;
            if(!FLOOR0) begin
                FLOOR0 = 1'b1;
            end
            if(FULL) begin
                FULL = 1'b0;
            end
        end
        if ((OUT1 == 1) && (firstFloor >0) && (firstFloor <= 500)) begin
            CARS  = CARS -1;
            AVAILABLE = AVAILABLE +1;
            if(!FLOOR1) begin
                FLOOR1 = 1'b1;
            end
            if(FULL) begin
                FULL = 1'b0;
            end
        end
    end
endmodule

module top;
    reg in,out0,out1;
    wire [31:0] cars;
    wire [31:0] available;
    wire full, floor0, floor1; 

    parkingManager dum(in,out0,out1,cars,available,full,floor0,floor1);
    initial begin
        $dumpfile("itp17210.vcd");
        $dumpvars(0);
        in = 1'b0;
        out0 = 1'b0;
        out1 = 1'b0;

        while (!full) begin
          case ($urandom%3)
                0 : begin
                    in = 1'b1;
                    #5 in = 1'b0;
                  end
                1 : begin
                    if(cars >0) begin
                        out0 = 1'b1;
                        #5 out0 = 1'b0;
                    end
                end
                2 : begin
                    if(cars >500) begin
                        out1 = 1'b1;
                        #5 out1 = 1'b0;
                    end
                end
            endcase
        end
    end
 endmodule

itp17210.vcd
$date
	Fri Jun 29 12:03:00 2018
$end
$version
	Icarus Verilog
$end
$timescale
	1s
$end
$scope module top $end
$var wire 32 ! available [31:0] $end
$var wire 32 " cars [31:0] $end
$var wire 1 # floor0 $end
$var wire 1 $ floor1 $end
$var wire 1 % full $end
$var reg 1 & in $end
$var reg 1 ' out0 $end
$var reg 1 ( out1 $end
$scope module dum $end
$var wire 1 ) IN $end
$var wire 1 * OUT0 $end
$var wire 1 + OUT1 $end
$var reg 32 , AVAILABLE [31:0] $end
$var reg 32 - CARS [31:0] $end
$var reg 1 . FLOOR0 $end
$var reg 1 / FLOOR1 $end
$var reg 1 0 FULL $end
$var reg 32 1 firstFloor [31:0] $end
$var reg 32 2 zeroFloor [31:0] $end
$upscope $end
$upscope $end
$enddefinitions $end
#0
$dumpvars
b1 2
b0 1
00
1/
1.
b1 -
b1111100111 ,
0+
0*
1)
0(
0'
1&
0%
1$
1#
b1 "
b1111100111 !
$end
#5
b1111101000 ,
b1111101000 !
b0 -
b0 "
1'
1*
0&
0)
#10
b10 2
b1111100111 ,
b1111100111 !
b1 -
b1 "
1&
1)
0'
0*
#15
b11 2
b1111100110 ,
b1111100110 !
b10 -
b10 "
1&
1)
#20
b1111100111 ,
b1111100111 !
b1 -
b1 "
1'
1*
0&
0)
#25
b100 2
b1111100110 ,
b1111100110 !
b10 -
b10 "
1&
1)
0'
0*
#30
b101 2
b1111100101 ,
b1111100101 !
b11 -
b11 "
1&
1)
#35
b1111100110 ,
b1111100110 !
b10 -
b10 "
1'
1*
0&
0)
#40
b1111100111 ,
b1111100111 !
b1 -
b1 "
1'
1*
#45
b1111101000 ,
b1111101000 !
b0 -
b0 "
1'
1*
#50
b110 2
b1111100111 ,
b1111100111 !
b1 -
b1 "
1&
1)
0'
0*
#55
b1111101000 ,
b1111101000 !
b0 -
b0 "
1'
1*
0&
0)
#60
b111 2
b1111100111 ,
b1111100111 !
b1 -
b1 "
1&
1)
0'
0*
#65
b1000 2
b1111100110 ,
b1111100110 !
b10 -
b10 "
1&
1)
#70
b1001 2
b1111100101 ,
b1111100101 !
b11 -
b11 "
1&
1)
#75
b1010 2
b1111100100 ,
b1111100100 !
b100 -
b100 "
1&
1)
#80
b1111100101 ,
b1111100101 !
b11 -
b11 "
1'
1*
0&
0)
#85
b1111100110 ,
b1111100110 !
b10 -
b10 "
1'
1*
#90
b1111100111 ,
b1111100111 !
b1 -
b1 "
1'
1*
#95
b1111101000 ,
b1111101000 !
b0 -
b0 "
1'
1*
#100
b1011 2
b1111100111 ,
b1111100111 !
b1 -
b1 "
1&
1)
0'
0*
#105
b1111101000 ,
b1111101000 !
b0 -
b0 "
1'
1*
0&
0)
#110
b1100 2
b1111100111 ,
b1111100111 !
b1 -
b1 "
1&
1)
0'
0*
#115
b1111101000 ,
b1111101000 !
b0 -
b0 "
1'
1*
0&
0)
#120
b1101 2
b1111100111 ,
b1111100111 !
b1 -
b1 "
1&
1)
0'
0*
#125
b1110 2
b1111100110 ,
b1111100110 !
b10 -
b10 "
1&
1)
#130
b1111 2
b1111100101 ,
b1111100101 !
b11 -
b11 "
1&
1)
#135
b1111100110 ,
b1111100110 !
b10 -
b10 "
1'
1*
0&
0)
#140
b1111100111 ,
b1111100111 !
b1 -
b1 "
1'
1*
#145
b10000 2
b1111100110 ,
b1111100110 !
b10 -
b10 "
1&
1)
0'
0*
#150
b1111100111 ,
b1111100111 !
b1 -
b1 "
1'
1*
0&
0)
#155
b10001 2
b1111100110 ,
b1111100110 !
b10 -
b10 "
1&
1)
0'
0*
#160
b1111100111 ,
b1111100111 !
b1 -
b1 "
1'
1*
0&
0)
#165
b1111101000 ,
b1111101000 !
b0 -
b0 "
1'
1*
#170
b10010 2
b1111100111 ,
b1111100111 !
b1 -
b1 "
1&
1)
0'
0*
#175
b10011 2
b1111100110 ,
b1111100110 !
b10 -
b10 "
1&
1)
#180
b10100 2
b1111100101 ,
b1111100101 !
b11 -
b11 "
1&
1)
#185
b10101 2
b1111100100 ,
b1111100100 !
b100 -
b100 "
1&
1)
#190
b1111100101 ,
b1111100101 !
b11 -
b11 "
1'
1*
0&
0)
#195
b1111100110 ,
b1111100110 !
b10 -
b10 "
1'
1*
#200
b1111100111 ,
b1111100111 !
b1 -
b1 "
1'
1*
#205
b10110 2
b1111100110 ,
b1111100110 !
b10 -
b10 "
1&
1)
0'
0*
#210
b10111 2
b1111100101 ,
b1111100101 !
b11 -
b11 "
1&
1)
#215
b1111100110 ,
b1111100110 !
b10 -
b10 "
1'
1*
0&
0)
#220
b11000 2
b1111100101 ,
b1111100101 !
b11 -
b11 "
1&
1)
0'
0*
#225
b1111100110 ,
b1111100110 !
b10 -
b10 "
1'
1*
0&
0)
#230
b11001 2
b1111100101 ,
b1111100101 !
b11 -
b11 "
1&
1)
0'
0*
#235
b1111100110 ,
b1111100110 !
b10 -
b10 "
1'
1*
0&
0)
#240
b1111100111 ,
b1111100111 !
b1 -
b1 "
1'
1*
#245
b1111101000 ,
b1111101000 !
b0 -
b0 "
1'
1*
#250
b11010 2
b1111100111 ,
b1111100111 !
b1 -
b1 "
1&
1)
0'
0*
#255
b11011 2
b1111100110 ,
b1111100110 !
b10 -
b10 "
1&
1)
#260
b1111100111 ,
b1111100111 !
b1 -
b1 "
1'
1*
0&
0)
#265
b1111101000 ,
b1111101000 !
b0 -
b0 "
1'
1*
#270
b11100 2
b1111100111 ,
b1111100111 !
b1 -
b1 "
1&
1)
0'
0*
#275
b11101 2
b1111100110 ,
b1111100110 !
b10 -
b10 "
1&
1)
#280
b1111100111 ,
b1111100111 !
b1 -
b1 "
1'
1*
0&
0)
#285
b1111101000 ,
b1111101000 !
b0 -
b0 "
1'
1*
#290
b11110 2
b1111100111 ,
b1111100111 !
b1 -
b1 "
1&
1)
0'
0*
#295
b11111 2
b1111100110 ,
b1111100110 !
b10 -
b10 "
1&
1)
#300
b100000 2
b1111100101 ,
b1111100101 !
b11 -
b11 "
1&
1)
#305
b100001 2
b1111100100 ,
b1111100100 !
b100 -
b100 "
1&
1)
#310
b100010 2
b1111100011 ,
b1111100011 !
b101 -
b101 "
1&
1)
#315
b1111100100 ,
b1111100100 !
b100 -
b100 "
1'
1*
0&
0)
#320
b100011 2
b1111100011 ,
b1111100011 !
b101 -
b101 "
1&
1)
0'
0*
#325
b100100 2
b1111100010 ,
b1111100010 !
b110 -
b110 "
1&
1)
#330
b100101 2
b1111100001 ,
b1111100001 !
b111 -
b111 "
1&
1)
#335
b100110 2
b1111100000 ,
b1111100000 !
b1000 -
b1000 "
1&
1)
#340
b1111100001 ,
b1111100001 !
b111 -
b111 "
1'
1*
0&
0)
#345
b1111100010 ,
b1111100010 !
b110 -
b110 "
1'
1*
#350
b100111 2
b1111100001 ,
b1111100001 !
b111 -
b111 "
1&
1)
0'
0*
#355
b1111100010 ,
b1111100010 !
b110 -
b110 "
1'
1*
0&
0)
#360
b1111100011 ,
b1111100011 !
b101 -
b101 "
1'
1*
#365
b101000 2
b1111100010 ,
b1111100010 !
b110 -
b110 "
1&
1)
0'
0*
#370
b1111100011 ,
b1111100011 !
b101 -
b101 "
1'
1*
0&
0)
#375
b101001 2
b1111100010 ,
b1111100010 !
b110 -
b110 "
1&
1)
0'
0*
#380
b101010 2
b1111100001 ,
b1111100001 !
b111 -
b111 "
1&
1)
#385
b1111100010 ,
b1111100010 !
b110 -
b110 "
1'
1*
0&
0)
#390
b1111100011 ,
b1111100011 !
b101 -
b101 "
1'
1*
#395
b1111100100 ,
b1111100100 !
b100 -
b100 "
1'
1*
#400
b101011 2
b1111100011 ,
b1111100011 !
b101 -
b101 "
1&
1)
0'
0*
#405
b101100 2
b1111100010 ,
b1111100010 !
b110 -
b110 "
1&
1)
#410
b1111100011 ,
b1111100011 !
b101 -
b101 "
1'
1*
0&
0)
#415
b101101 2
b1111100010 ,
b1111100010 !
b110 -
b110 "
1&
1)
0'
0*
#420
b101110 2
b1111100001 ,
b1111100001 !
b111 -
b111 "
1&
1)
#425
b1111100010 ,
b1111100010 !
b110 -
b110 "
1'
1*
0&
0)
#430
b101111 2
b1111100001 ,
b1111100001 !
b111 -
b111 "
1&
1)
0'
0*
#435
b1111100010 ,
b1111100010 !
b110 -
b110 "
1'
1*
0&
0)
#440
b1111100011 ,
b1111100011 !
b101 -
b101 "
1'
1*
#445
b110000 2
b1111100010 ,
b1111100010 !
b110 -
b110 "
1&
1)
0'
0*
#450
b1111100011 ,
b1111100011 !
b101 -
b101 "
1'
1*
0&
0)
#455
b110001 2
b1111100010 ,
b1111100010 !
b110 -
b110 "
1&
1)
0'
0*
#460
b1111100011 ,
b1111100011 !
b101 -
b101 "
1'
1*
0&
0)
#465
b1111100100 ,
b1111100100 !
b100 -
b100 "
1'
1*
#470
b1111100101 ,
b1111100101 !
b11 -
b11 "
1'
1*
#475
b1111100110 ,
b1111100110 !
b10 -
b10 "
1'
1*
#480
b110010 2
b1111100101 ,
b1111100101 !
b11 -
b11 "
1&
1)
0'
0*
#485
b110011 2
b1111100100 ,
b1111100100 !
b100 -
b100 "
1&
1)
#490
b1111100101 ,
b1111100101 !
b11 -
b11 "
1'
1*
0&
0)
#495
b1111100110 ,
b1111100110 !
b10 -
b10 "
1'
1*
#500
b110100 2
b1111100101 ,
b1111100101 !
b11 -
b11 "
1&
1)
0'
0*
#505
b110101 2
b1111100100 ,
b1111100100 !
b100 -
b100 "
1&
1)
#510
b110110 2
b1111100011 ,
b1111100011 !
b101 -
b101 "
1&
1)
#515
b1111100100 ,
b1111100100 !
b100 -
b100 "
1'
1*
0&
0)
#520
b110111 2
b1111100011 ,
b1111100011 !
b101 -
b101 "
1&
1)
0'
0*
#525
b1111100100 ,
b1111100100 !
b100 -
b100 "
1'
1*
0&
0)
#530
b111000 2
b1111100011 ,
b1111100011 !
b101 -
b101 "
1&
1)
0'
0*
#535
b111001 2
b1111100010 ,
b1111100010 !
b110 -
b110 "
1&
1)
#540
b1111100011 ,
b1111100011 !
b101 -
b101 "
1'
1*
0&
0)
#545
b1111100100 ,
b1111100100 !
b100 -
b100 "
1'
1*
#550
b1111100101 ,
b1111100101 !
b11 -
b11 "
1'
1*
#555
b1111100110 ,
b1111100110 !
b10 -
b10 "
1'
1*
#560
b111010 2
b1111100101 ,
b1111100101 !
b11 -
b11 "
1&
1)
0'
0*
#565
b111011 2
b1111100100 ,
b1111100100 !
b100 -
b100 "
1&
1)
#570
b1111100101 ,
b1111100101 !
b11 -
b11 "
1'
1*
0&
0)
#575
b111100 2
b1111100100 ,
b1111100100 !
b100 -
b100 "
1&
1)
0'
0*
#580
b1111100101 ,
b1111100101 !
b11 -
b11 "
1'
1*
0&
0)
#585
b1111100110 ,
b1111100110 !
b10 -
b10 "
1'
1*
#590
b1111100111 ,
b1111100111 !
b1 -
b1 "
1'
1*
#595
b111101 2
b1111100110 ,
b1111100110 !
b10 -
b10 "
1&
1)
0'
0*
#600
b111110 2
b1111100101 ,
b1111100101 !
b11 -
b11 "
1&
1)
#605
b111111 2
b1111100100 ,
b1111100100 !
b100 -
b100 "
1&
1)
#610
b1000000 2
b1111100011 ,
b1111100011 !
b101 -
b101 "
1&
1)
#615
b1111100100 ,
b1111100100 !
b100 -
b100 "
1'
1*
0&
0)
#620
b1000001 2
b1111100011 ,
b1111100011 !
b101 -
b101 "
1&
1)
0'
0*
#625
b1111100100 ,
b1111100100 !
b100 -
b100 "
1'
1*
0&
0)
#630
b1111100101 ,
b1111100101 !
b11 -
b11 "
1'
1*
#635
b1000010 2
b1111100100 ,
b1111100100 !
b100 -
b100 "
1&
1)
0'
0*
#640
b1000011 2
b1111100011 ,
b1111100011 !
b101 -
b101 "
1&
1)
#645
b1111100100 ,
b1111100100 !
b100 -
b100 "
1'
1*
0&
0)
#650
b1111100101 ,
b1111100101 !
b11 -
b11 "
1'
1*
#655
b1111100110 ,
b1111100110 !
b10 -
b10 "
1'
1*
#660
b1111100111 ,
b1111100111 !
b1 -
b1 "
1'
1*
#665
b1000100 2
b1111100110 ,
b1111100110 !
b10 -
b10 "
1&
1)
0'
0*
#670
b1000101 2
b1111100101 ,
b1111100101 !
b11 -
b11 "
1&
1)
#675
b1000110 2
b1111100100 ,
b1111100100 !
b100 -
b100 "
1&
1)
#680
b1000111 2
b1111100011 ,
b1111100011 !
b101 -
b101 "
1&
1)
#685
b1001000 2
b1111100010 ,
b1111100010 !
b110 -
b110 "
1&
1)
#690
b1001001 2
b1111100001 ,
b1111100001 !
b111 -
b111 "
1&
1)
#695
b1111100010 ,
b1111100010 !
b110 -
b110 "
1'
1*
0&
0)
#700
b1111100011 ,
b1111100011 !
b101 -
b101 "
1'
1*
#705
b1111100100 ,
b1111100100 !
b100 -
b100 "
1'
1*
#710
b1001010 2
b1111100011 ,
b1111100011 !
b101 -
b101 "
1&
1)
0'
0*
#715
b1001011 2
b1111100010 ,
b1111100010 !
b110 -
b110 "
1&
1)
#720
b1111100011 ,
b1111100011 !
b101 -
b101 "
1'
1*
0&
0)
#725
b1001100 2
b1111100010 ,
b1111100010 !
b110 -
b110 "
1&
1)
0'
0*
#730
b1001101 2
b1111100001 ,
b1111100001 !
b111 -
b111 "
1&
1)
#735
b1001110 2
b1111100000 ,
b1111100000 !
b1000 -
b1000 "
1&
1)
#740
b1001111 2
b1111011111 ,
b1111011111 !
b1001 -
b1001 "
1&
1)
#745
b1111100000 ,
b1111100000 !
b1000 -
b1000 "
1'
1*
0&
0)
#750
b1111100001 ,
b1111100001 !
b111 -
b111 "
1'
1*
#755
b1010000 2
b1111100000 ,
b1111100000 !
b1000 -
b1000 "
1&
1)
0'
0*
#760
b1111100001 ,
b1111100001 !
b111 -
b111 "
1'
1*
0&
0)
#765
b1010001 2
b1111100000 ,
b1111100000 !
b1000 -
b1000 "
1&
1)
0'
0*
#770
b1010010 2
b1111011111 ,
b1111011111 !
b1001 -
b1001 "
1&
1)
#775
b1111100000 ,
b1111100000 !
b1000 -
b1000 "
1'
1*
0&
0)
#780
b1010011 2
b1111011111 ,
b1111011111 !
b1001 -
b1001 "
1&
1)
0'
0*
#785
b1111100000 ,
b1111100000 !
b1000 -
b1000 "
1'
1*
0&
0)
#790
b1111100001 ,
b1111100001 !
b111 -
b111 "
1'
1*
#795
b1111100010 ,
b1111100010 !
b110 -
b110 "
1'
1*
#800
b1010100 2
b1111100001 ,
b1111100001 !
b111 -
b111 "
1&
1)
0'
0*
#805
b1010101 2
b1111100000 ,
b1111100000 !
b1000 -
b1000 "
1&
1)
#810
b1111100001 ,
b1111100001 !
b111 -
b111 "
1'
1*
0&
0)
#815
b1111100010 ,
b1111100010 !
b110 -
b110 "
1'
1*
#820
b1111100011 ,
b1111100011 !
b101 -
b101 "
1'
1*
#825
b1111100100 ,
b1111100100 !
b100 -
b100 "
1'
1*
#830
b1010110 2
b1111100011 ,
b1111100011 !
b101 -
b101 "
1&
1)
0'
0*
#835
b1010111 2
b1111100010 ,
b1111100010 !
b110 -
b110 "
1&
1)
#840
b1111100011 ,
b1111100011 !
b101 -
b101 "
1'
1*
0&
0)
#845
b1111100100 ,
b1111100100 !
b100 -
b100 "
1'
1*
#850
b1011000 2
b1111100011 ,
b1111100011 !
b101 -
b101 "
1&
1)
0'
0*
#855
b1111100100 ,
b1111100100 !
b100 -
b100 "
1'
1*
0&
0)
#860
b1011001 2
b1111100011 ,
b1111100011 !
b101 -
b101 "
1&
1)
0'
0*
#865
b1111100100 ,
b1111100100 !
b100 -
b100 "
1'
1*
0&
0)
#870
b1011010 2
b1111100011 ,
b1111100011 !
b101 -
b101 "
1&
1)
0'
0*
#875
b1011011 2
b1111100010 ,
b1111100010 !
b110 -
b110 "
1&
1)
#880
b1011100 2
b1111100001 ,
b1111100001 !
b111 -
b111 "
1&
1)
#885
b1111100010 ,
b1111100010 !
b110 -
b110 "
1'
1*
0&
0)
#890
b1111100011 ,
b1111100011 !
b101 -
b101 "
1'
1*
#895
b1111100100 ,
b1111100100 !
b100 -
b100 "
1'
1*
#900
b1111100101 ,
b1111100101 !
b11 -
b11 "
1'
1*
#905
b1011101 2
b1111100100 ,
b1111100100 !
b100 -
b100 "
1&
1)
0'
0*
#910
b1011110 2
b1111100011 ,
b1111100011 !
b101 -
b101 "
1&
1)
#915
b1011111 2
b1111100010 ,
b1111100010 !
b110 -
b110 "
1&
1)
#920
b1100000 2
b1111100001 ,
b1111100001 !
b111 -
b111 "
1&
1)
#925
b1100001 2
b1111100000 ,
b1111100000 !
b1000 -
b1000 "
1&
1)
#930
b1111100001 ,
b1111100001 !
b111 -
b111 "
1'
1*
0&
0)
#935
b1111100010 ,
b1111100010 !
b110 -
b110 "
1'
1*
#940
b1100010 2
b1111100001 ,
b1111100001 !
b111 -
b111 "
1&
1)
0'
0*
#945
b1100011 2
b1111100000 ,
b1111100000 !
b1000 -
b1000 "
1&
1)
#950
b1111100001 ,
b1111100001 !
b111 -
b111 "
1'
1*
0&
0)
#955
b1111100010 ,
b1111100010 !
b110 -
b110 "
1'
1*
#960
b1100100 2
b1111100001 ,
b1111100001 !
b111 -
b111 "
1&
1)
0'
0*
#965
b1100101 2
b1111100000 ,
b1111100000 !
b1000 -
b1000 "
1&
1)
#970
b1111100001 ,
b1111100001 !
b111 -
b111 "
1'
1*
0&
0)
#975
b1100110 2
b1111100000 ,
b1111100000 !
b1000 -
b1000 "
1&
1)
0'
0*
#980
b1111100001 ,
b1111100001 !
b111 -
b111 "
1'
1*
0&
0)
#985
b1111100010 ,
b1111100010 !
b110 -
b110 "
1'
1*
#990
b1111100011 ,
b1111100011 !
b101 -
b101 "
1'
1*
#995
b1111100100 ,
b1111100100 !
b100 -
b100 "
1'
1*
#1000
b1111100101 ,
b1111100101 !
b11 -
b11 "
1'
1*
#1005
b1111100110 ,
b1111100110 !
b10 -
b10 "
1'
1*
#1010
b1111100111 ,
b1111100111 !
b1 -
b1 "
1'
1*
#1015
b1100111 2
b1111100110 ,
b1111100110 !
b10 -
b10 "
1&
1)
0'
0*
#1020
b1101000 2
b1111100101 ,
b1111100101 !
b11 -
b11 "
1&
1)
#1025
b1101001 2
b1111100100 ,
b1111100100 !
b100 -
b100 "
1&
1)
#1030
b1111100101 ,
b1111100101 !
b11 -
b11 "
1'
1*
0&
0)
#1035
b1111100110 ,
b1111100110 !
b10 -
b10 "
1'
1*
#1040
b1101010 2
b1111100101 ,
b1111100101 !
b11 -
b11 "
1&
1)
0'
0*
#1045
b1101011 2
b1111100100 ,
b1111100100 !
b100 -
b100 "
1&
1)
#1050
b1111100101 ,
b1111100101 !
b11 -
b11 "
1'
1*
0&
0)
#1055
b1101100 2
b1111100100 ,
b1111100100 !
b100 -
b100 "
1&
1)
0'
0*
#1060
b1111100101 ,
b1111100101 !
b11 -
b11 "
1'
1*
0&
0)
#1065
b1111100110 ,
b1111100110 !
b10 -
b10 "
1'
1*
#1070
b1101101 2
b1111100101 ,
b1111100101 !
b11 -
b11 "
1&
1)
0'
0*
#1075
b1101110 2
b1111100100 ,
b1111100100 !
b100 -
b100 "
1&
1)
#1080
b1101111 2
b1111100011 ,
b1111100011 !
b101 -
b101 "
1&
1)
#1085
b1111100100 ,
b1111100100 !
b100 -
b100 "
1'
1*
0&
0)
#1090
b1111100101 ,
b1111100101 !
b11 -
b11 "
1'
1*
#1095
b1111100110 ,
b1111100110 !
b10 -
b10 "
1'
1*
#1100
b1111100111 ,
b1111100111 !
b1 -
b1 "
1'
1*
#1105
b1110000 2
b1111100110 ,
b1111100110 !
b10 -
b10 "
1&
1)
0'
0*
#1110
b1111100111 ,
b1111100111 !
b1 -
b1 "
1'
1*
0&
0)
#1115
b1110001 2
b1111100110 ,
b1111100110 !
b10 -
b10 "
1&
1)
0'
0*
#1120
b1110010 2
b1111100101 ,
b1111100101 !
b11 -
b11 "
1&
1)
#1125
b1110011 2
b1111100100 ,
b1111100100 !
b100 -
b100 "
1&
1)
#1130
b1111100101 ,
b1111100101 !
b11 -
b11 "
1'
1*
0&
0)
#1135
b1111100110 ,
b1111100110 !
b10 -
b10 "
1'
1*
#1140
b1110100 2
b1111100101 ,
b1111100101 !
b11 -
b11 "
1&
1)
0'
0*
#1145
b1110101 2
b1111100100 ,
b1111100100 !
b100 -
b100 "
1&
1)
#1150
b1110110 2
b1111100011 ,
b1111100011 !
b101 -
b101 "
1&
1)
#1155
b1111100100 ,
b1111100100 !
b100 -
b100 "
1'
1*
0&
0)
#1160
b1110111 2
b1111100011 ,
b1111100011 !
b101 -
b101 "
1&
1)
0'
0*
#1165
b1111100100 ,
b1111100100 !
b100 -
b100 "
1'
1*
0&
0)
#1170
b1111000 2
b1111100011 ,
b1111100011 !
b101 -
b101 "
1&
1)
0'
0*
#1175
b1111001 2
b1111100010 ,
b1111100010 !
b110 -
b110 "
1&
1)
#1180
b1111100011 ,
b1111100011 !
b101 -
b101 "
1'
1*
0&
0)
#1185
b1111010 2
b1111100010 ,
b1111100010 !
b110 -
b110 "
1&
1)
0'
0*
#1190
b1111100011 ,
b1111100011 !
b101 -
b101 "
1'
1*
0&
0)
#1195
b1111100100 ,
b1111100100 !
b100 -
b100 "
1'
1*
#1200
b1111011 2
b1111100011 ,
b1111100011 !
b101 -
b101 "
1&
1)
0'
0*
#1205
b1111100 2
b1111100010 ,
b1111100010 !
b110 -
b110 "
1&
1)
#1210
b1111101 2
b1111100001 ,
b1111100001 !
b111 -
b111 "
1&
1)
#1215
b1111110 2
b1111100000 ,
b1111100000 !
b1000 -
b1000 "
1&
1)
#1220
b1111111 2
b1111011111 ,
b1111011111 !
b1001 -
b1001 "
1&
1)
#1225
b1111100000 ,
b1111100000 !
b1000 -
b1000 "
1'
1*
0&
0)
#1230
b10000000 2
b1111011111 ,
b1111011111 !
b1001 -
b1001 "
1&
1)
0'
0*
#1235
b10000001 2
b1111011110 ,
b1111011110 !
b1010 -
b1010 "
1&
1)
#1240
b10000010 2
b1111011101 ,
b1111011101 !
b1011 -
b1011 "
1&
1)
#1245
b1111011110 ,
b1111011110 !
b1010 -
b1010 "
1'
1*
0&
0)
#1250
b10000011 2
b1111011101 ,
b1111011101 !
b1011 -
b1011 "
1&
1)
0'
0*
#1255
b1111011110 ,
b1111011110 !
b1010 -
b1010 "
1'
1*
0&
0)
#1260
b10000100 2
b1111011101 ,
b1111011101 !
b1011 -
b1011 "
1&
1)
0'
0*
#1265
b1111011110 ,
b1111011110 !
b1010 -
b1010 "
1'
1*
0&
0)
#1270
b10000101 2
b1111011101 ,
b1111011101 !
b1011 -
b1011 "
1&
1)
0'
0*
#1275
b10000110 2
b1111011100 ,
b1111011100 !
b1100 -
b1100 "
1&
1)
#1280
b10000111 2
b1111011011 ,
b1111011011 !
b1101 -
b1101 "
1&
1)
#1285
b10001000 2
b1111011010 ,
b1111011010 !
b1110 -
b1110 "
1&
1)
#1290
b10001001 2
b1111011001 ,
b1111011001 !
b1111 -
b1111 "
1&
1)
#1295
b10001010 2
b1111011000 ,
b1111011000 !
b10000 -
b10000 "
1&
1)
#1300
b1111011001 ,
b1111011001 !
b1111 -
b1111 "
1'
1*
0&
0)
#1305
b10001011 2
b1111011000 ,
b1111011000 !
b10000 -
b10000 "
1&
1)
0'
0*
#1310
b1111011001 ,
b1111011001 !
b1111 -
b1111 "
1'
1*
0&
0)
#1315
b10001100 2
b1111011000 ,
b1111011000 !
b10000 -
b10000 "
1&
1)
0'
0*
#1320
b10001101 2
b1111010111 ,
b1111010111 !
b10001 -
b10001 "
1&
1)
#1325
b1111011000 ,
b1111011000 !
b10000 -
b10000 "
1'
1*
0&
0)
#1330
b10001110 2
b1111010111 ,
b1111010111 !
b10001 -
b10001 "
1&
1)
0'
0*
#1335
b1111011000 ,
b1111011000 !
b10000 -
b10000 "
1'
1*
0&
0)
#1340
b10001111 2
b1111010111 ,
b1111010111 !
b10001 -
b10001 "
1&
1)
0'
0*
#1345
b10010000 2
b1111010110 ,
b1111010110 !
b10010 -
b10010 "
1&
1)
#1350
b10010001 2
b1111010101 ,
b1111010101 !
b10011 -
b10011 "
1&
1)
#1355
b1111010110 ,
b1111010110 !
b10010 -
b10010 "
1'
1*
0&
0)
#1360
b1111010111 ,
b1111010111 !
b10001 -
b10001 "
1'
1*
#1365
b1111011000 ,
b1111011000 !
b10000 -
b10000 "
1'
1*
#1370
b1111011001 ,
b1111011001 !
b1111 -
b1111 "
1'
1*
#1375
b10010010 2
b1111011000 ,
b1111011000 !
b10000 -
b10000 "
1&
1)
0'
0*
#1380
b1111011001 ,
b1111011001 !
b1111 -
b1111 "
1'
1*
0&
0)
#1385
b1111011010 ,
b1111011010 !
b1110 -
b1110 "
1'
1*
#1390
b1111011011 ,
b1111011011 !
b1101 -
b1101 "
1'
1*
#1395
b1111011100 ,
b1111011100 !
b1100 -
b1100 "
1'
1*
#1400
b1111011101 ,
b1111011101 !
b1011 -
b1011 "
1'
1*
#1405
b10010011 2
b1111011100 ,
b1111011100 !
b1100 -
b1100 "
1&
1)
0'
0*
#1410
b1111011101 ,
b1111011101 !
b1011 -
b1011 "
1'
1*
0&
0)
#1415
b1111011110 ,
b1111011110 !
b1010 -
b1010 "
1'
1*
#1420
b1111011111 ,
b1111011111 !
b1001 -
b1001 "
1'
1*
#1425
b10010100 2
b1111011110 ,
b1111011110 !
b1010 -
b1010 "
1&
1)
0'
0*
#1430
b1111011111 ,
b1111011111 !
b1001 -
b1001 "
1'
1*
0&
0)
#1435
b10010101 2
b1111011110 ,
b1111011110 !
b1010 -
b1010 "
1&
1)
0'
0*
#1440
b10010110 2
b1111011101 ,
b1111011101 !
b1011 -
b1011 "
1&
1)
#1445
b10010111 2
b1111011100 ,
b1111011100 !
b1100 -
b1100 "
1&
1)
#1450
b1111011101 ,
b1111011101 !
b1011 -
b1011 "
1'
1*
0&
0)
#1455
b10011000 2
b1111011100 ,
b1111011100 !
b1100 -
b1100 "
1&
1)
0'
0*
#1460
b1111011101 ,
b1111011101 !
b1011 -
b1011 "
1'
1*
0&
0)
#1465
b1111011110 ,
b1111011110 !
b1010 -
b1010 "
1'
1*
#1470
b10011001 2
b1111011101 ,
b1111011101 !
b1011 -
b1011 "
1&
1)
0'
0*
#1475
b1111011110 ,
b1111011110 !
b1010 -
b1010 "
1'
1*
0&
0)
#1480
b1111011111 ,
b1111011111 !
b1001 -
b1001 "
1'
1*
#1485
b10011010 2
b1111011110 ,
b1111011110 !
b1010 -
b1010 "
1&
1)
0'
0*
#1490
b1111011111 ,
b1111011111 !
b1001 -
b1001 "
1'
1*
0&
0)
#1495
b1111100000 ,
b1111100000 !
b1000 -
b1000 "
1'
1*
#1500
b1111100001 ,
b1111100001 !
b111 -
b111 "
1'
1*
#1505
b1111100010 ,
b1111100010 !
b110 -
b110 "
1'
1*
#1510
b1111100011 ,
b1111100011 !
b101 -
b101 "
1'
1*
#1515
b10011011 2
b1111100010 ,
b1111100010 !
b110 -
b110 "
1&
1)
0'
0*
#1520
b10011100 2
b1111100001 ,
b1111100001 !
b111 -
b111 "
1&
1)
#1525
b10011101 2
b1111100000 ,
b1111100000 !
b1000 -
b1000 "
1&
1)
#1530
b1111100001 ,
b1111100001 !
b111 -
b111 "
1'
1*
0&
0)
#1535
b10011110 2
b1111100000 ,
b1111100000 !
b1000 -
b1000 "
1&
1)
0'
0*
#1540
b1111100001 ,
b1111100001 !
b111 -
b111 "
1'
1*
0&
0)
#1545
b1111100010 ,
b1111100010 !
b110 -
b110 "
1'
1*
#1550
b1111100011 ,
b1111100011 !
b101 -
b101 "
1'
1*
